{
  "name": "@microsoft/site-utilities",
  "entries": [
    {
      "date": "Thu, 20 May 2021 07:24:10 GMT",
      "tag": "@microsoft/site-utilities_v0.9.0",
      "version": "0.9.0",
      "comments": {
        "patch": [
          {
            "comment": "Bump @microsoft/fast-tooling-react to v2.8.8",
            "author": "john.kreitlow@microsoft.com",
            "commit": "c7db517ac34ee6f0e5454bbf395711f464b438a0",
            "package": "@microsoft/site-utilities"
          }
        ]
      }
    },
    {
      "date": "Wed, 19 May 2021 23:37:36 GMT",
      "tag": "@microsoft/site-utilities_v0.9.0",
      "version": "0.9.0",
      "comments": {
        "none": [
          {
            "comment": "Bump @microsoft/fast-tooling to v0.19.1",
            "author": "nicholasrice@users.noreply.github.com",
            "commit": "7fadbeb59267e4dc976cd9f56ee5b61f26e4ae20",
            "package": "@microsoft/site-utilities"
          },
          {
            "comment": "Bump @microsoft/fast-tooling-react to v2.8.7",
            "author": "7559015+janechu@users.noreply.github.com",
            "commit": "653bb537e44c365a63b5cbefd74774a0a4be1d08",
            "package": "@microsoft/site-utilities"
          }
        ],
        "patch": [
          {
            "comment": "Bump @microsoft/fast-foundation to v1.23.0",
            "author": "nicholasrice@users.noreply.github.com",
            "commit": "a433b6bcab871f24ccbe828b2023c256942d40af",
            "package": "@microsoft/site-utilities"
          }
        ]
      }
    },
    {
      "date": "Sun, 02 May 2021 07:18:00 GMT",
      "tag": "@microsoft/site-utilities_v0.9.0",
      "version": "0.9.0",
      "comments": {
        "patch": [
          {
            "comment": "Bump @microsoft/fast-tooling-react to v2.8.6",
            "author": "44823142+williamw2@users.noreply.github.com",
            "commit": "6fda54d6e00d4620dc1bdc140884acc85a7ce24a",
            "package": "@microsoft/site-utilities"
          }
        ]
      }
    },
    {
      "date": "Thu, 29 Apr 2021 07:19:40 GMT",
      "tag": "@microsoft/site-utilities_v0.9.0",
      "version": "0.9.0",
      "comments": {
        "patch": [
          {
            "comment": "Bump @microsoft/fast-tooling-react to v2.8.5",
            "author": "7559015+janechu@users.noreply.github.com",
            "commit": "9357f10ca02a6a2785ac08ad2928d0a0531c03d6",
            "package": "@microsoft/site-utilities"
          }
        ]
      }
    },
    {
      "date": "Sun, 25 Apr 2021 07:21:02 GMT",
      "tag": "@microsoft/site-utilities_v0.9.0",
      "version": "0.9.0",
      "comments": {
        "patch": [
          {
            "comment": "Bump @microsoft/fast-components to v1.20.4",
            "author": "nicholasrice@users.noreply.github.com",
            "commit": "048081bd5d85c62911d4a4105cbbd23c60ae446d",
            "package": "@microsoft/site-utilities"
          }
        ]
      }
    },
    {
      "date": "Thu, 22 Apr 2021 07:21:10 GMT",
      "tag": "@microsoft/site-utilities_v0.9.0",
      "version": "0.9.0",
      "comments": {
        "patch": [
          {
            "comment": "Bump @microsoft/fast-components to v1.20.3",
            "author": "chhol@microsoft.com",
            "commit": "07ca9bdfb7699dbc6b4a101aa9218856e98cca8b",
            "package": "@microsoft/site-utilities"
          }
        ],
        "none": [
          {
            "comment": "Bump @microsoft/fast-tooling-react to v2.8.3",
            "author": "44823142+williamw2@users.noreply.github.com",
            "commit": "72e6442cb7f473803b7cc972d76b9fa684b3df1a",
            "package": "@microsoft/site-utilities"
          }
        ]
      }
    },
    {
      "date": "Fri, 16 Apr 2021 01:19:08 GMT",
      "tag": "@microsoft/site-utilities_v0.9.0",
      "version": "0.9.0",
      "comments": {
        "none": [
          {
            "comment": "Bump @microsoft/fast-tooling-react to v2.8.1",
            "author": "7559015+janechu@users.noreply.github.com",
            "commit": "6130e34254ba97e5b7922b669e4e287cbb54585e",
            "package": "@microsoft/site-utilities"
          }
        ]
      }
    }
  ]
}
